gravis2/__init__.py
gravis2/_internal/__init__.py
gravis2/_internal/conversion/__init__.py
gravis2/_internal/conversion/_internal.py
gravis2/_internal/conversion/convert.py
gravis2/_internal/plotting/__init__.py
gravis2/_internal/plotting/d3.py
gravis2/_internal/plotting/data_structures.py
gravis2/_internal/plotting/rendering.py
gravis2/_internal/plotting/template_system.py
gravis2/_internal/plotting/three.py
gravis2/_internal/plotting/vis.py
gravis2/_internal/utils/__init__.py
gravis2/_internal/utils/args.py
gravis2/_internal/utils/operating_system.py
gravis2/_internal/utils/web.py
gravis2-0.1.0.dist-info/LICENSE
gravis2-0.1.0.dist-info/METADATA
gravis2-0.1.0.dist-info/WHEEL
gravis2-0.1.0.dist-info/top_level.txt
gravis2-0.1.0.dist-info/RECORD
